{
  "options":{
  	"APM": true,
  	"APM_interval": 0.005
  },

  "trace_custom": [
  ],
  "trace_vitis-ai-library": [
    "vitis::ai::ClassificationImp::run@libvitis_ai_library-classification.so",
    "vitis::ai::ConfigurableDpuTaskImp::run@libvitis_ai_library-dpu_task.so",
    "vitis::ai::DetectImp::run@libvitis_ai_library-facedetect.so",
    "vitis::ai::DpuTaskImp::run@libvitis_ai_library-dpu_task.so",
    "vitis::ai::DpuTaskImp::setImageBGR@libvitis_ai_library-dpu_task.so",
    "vitis::ai::DpuTaskImp::setImageRGB@libvitis_ai_library-dpu_task.so",
    "vitis::ai::FaceLandmarkImp::run@libvitis_ai_library-facelandmark.so",
    "vitis::ai::MultiTaskImp::run_8UC1@libvitis_ai_library-multitask.so",
    "vitis::ai::MultiTaskImp::run_8UC3@libvitis_ai_library-multitask.so",
    "vitis::ai::MultiTaskImp::run_it@libvitis_ai_library-multitask.so",
    "vitis::ai::OpenPoseImp::run@libvitis_ai_library-openpose.so",
    "vitis::ai::PoseDetectImp::run@libvitis_ai_library-posedetect.so",
    "vitis::ai::RefineDetImp::run@libvitis_ai_library-refinedet.so",
    "vitis::ai::ReidImp::run@libvitis_ai_library-reid.so",
    "vitis::ai::RoadLineImp::run@libvitis_ai_library-lanedetect.so",
    "vitis::ai::SSDImp::run@libvitis_ai_library-ssd.so",
    "vitis::ai::Segmentation8UC1::run@libvitis_ai_library-segmentation.so",
    "vitis::ai::Segmentation8UC3::run@libvitis_ai_library-segmentation.so",
    "vitis::ai::SegmentationImp::run_8UC1@libvitis_ai_library-segmentation.so",
    "vitis::ai::SegmentationImp::run_8UC3@libvitis_ai_library-segmentation.so",
    "vitis::ai::TFSSDImp::run@libvitis_ai_library-tfssd.so",
    "vitis::ai::YOLOv2Imp::run@libvitis_ai_library-yolov2.so",
    "vitis::ai::YOLOv3Imp::run@libvitis_ai_library-yolov3.so",
    "vitis::ai::croppedImage@libvitis_ai_library-classification.so",
    "vitis::ai::inception_preprocess@libvitis_ai_library-classification.so",
    "vitis::ai::init_tasks@libvitis_ai_library-dpu_task.so",
    "vitis::ai::slurp@libvitis_ai_library-dpu_task.so",
    "vitis::ai::vgg_preprocess@libvitis_ai_library-classification.so",
    "vitis::ai::yolov2::add_pixel@libvitis_ai_library-yolov2.so",
    "vitis::ai::yolov2::convertInputImage@libvitis_ai_library-yolov2.so",
    "vitis::ai::yolov2::convert_RGB@libvitis_ai_library-yolov2.so",
    "vitis::ai::yolov2::embed_image@libvitis_ai_library-yolov2.so",
    "vitis::ai::yolov2::fill_image@libvitis_ai_library-yolov2.so",
    "vitis::ai::yolov2::free_image@libvitis_ai_library-yolov2.so",
    "vitis::ai::yolov2::get_pixel@libvitis_ai_library-yolov2.so",
    "vitis::ai::yolov2::ipl_into_image@libvitis_ai_library-yolov2.so",
    "vitis::ai::yolov2::ipl_to_image@libvitis_ai_library-yolov2.so",
    "vitis::ai::yolov2::letterbox_image@libvitis_ai_library-yolov2.so",
    "vitis::ai::yolov2::load_image_cv@libvitis_ai_library-yolov2.so",
    "vitis::ai::yolov2::make_empty_image@libvitis_ai_library-yolov2.so",
    "vitis::ai::yolov2::make_image@libvitis_ai_library-yolov2.so",
    "vitis::ai::yolov2::resize_image@libvitis_ai_library-yolov2.so",
    "vitis::ai::yolov2::rgbgr_image@libvitis_ai_library-yolov2.so",
    "vitis::ai::yolov2::set_pixel@libvitis_ai_library-yolov2.so",
    "vitis::ai::yolov2::writefile@libvitis_ai_library-yolov2.so",
    "vitis::ai::yolov3::add_pixel@libvitis_ai_library-yolov3.so",
    "vitis::ai::yolov3::convertInputImage@libvitis_ai_library-yolov3.so",
    "vitis::ai::yolov3::convert_RGB@libvitis_ai_library-yolov3.so",
    "vitis::ai::yolov3::embed_image@libvitis_ai_library-yolov3.so",
    "vitis::ai::yolov3::fill_image@libvitis_ai_library-yolov3.so",
    "vitis::ai::yolov3::free_image@libvitis_ai_library-yolov3.so",
    "vitis::ai::yolov3::get_pixel@libvitis_ai_library-yolov3.so",
    "vitis::ai::yolov3::ipl_into_image@libvitis_ai_library-yolov3.so",
    "vitis::ai::yolov3::ipl_to_image@libvitis_ai_library-yolov3.so",
    "vitis::ai::yolov3::letterbox_image@libvitis_ai_library-yolov3.so",
    "vitis::ai::yolov3::letterbox_tf@libvitis_ai_library-yolov3.so",
    "vitis::ai::yolov3::load_image_cv@libvitis_ai_library-yolov3.so",
    "vitis::ai::yolov3::make_empty_image@libvitis_ai_library-yolov3.so",
    "vitis::ai::yolov3::make_image@libvitis_ai_library-yolov3.so",
    "vitis::ai::yolov3::resize_image@libvitis_ai_library-yolov3.so",
    "vitis::ai::yolov3::rgbgr_image@libvitis_ai_library-yolov3.so",
    "vitis::ai::yolov3::set_pixel@libvitis_ai_library-yolov3.so"
  ],
  "trace_xnnpp": [
    "scalar_dot_prod_neon@libvitis_ai_library-math.so",
    "scalar_prod_inplace_neon@libvitis_ai_library-math.so",
    "scalar_prod_neon@libvitis_ai_library-math.so",
    "select@libvitis_ai_library-math.so",
    "square_sum_neon@libvitis_ai_library-math.so",
    "sum_neon@libvitis_ai_library-math.so",
    "vitis::ai::FilterBox@libxnnpp-xnnpp.so",
    "vitis::ai::MultiTaskPostProcessImp::post_process_seg@libxnnpp-xnnpp.so",
    "vitis::ai::MultiTaskPostProcessImp::process_det@libxnnpp-xnnpp.so",
    "vitis::ai::MultiTaskPostProcessImp::process_seg@libxnnpp-xnnpp.so",
    "vitis::ai::MultiTaskPostProcessImp::process_seg_visualization@libxnnpp-xnnpp.so",
    "vitis::ai::NMS@libxnnpp-xnnpp.so",
    "vitis::ai::NormalizeInputData@libvitis_ai_library-math.so",
    "vitis::ai::NormalizeInputDataRGB@libvitis_ai_library-math.so",
    "vitis::ai::ReadBinMultiVec@libxnnpp-xnnpp.so",
    "vitis::ai::RefineDetPost::refine_det_post_process@libxnnpp-xnnpp.so",
    "vitis::ai::RoadLinePost::road_line_post_process@libxnnpp-xnnpp.so",
    "vitis::ai::SSDNormalizer::normalize_neon@libvitis_ai_library-math.so",
    "vitis::ai::SSDPost::ssd_post_process@libxnnpp-xnnpp.so",
    "vitis::ai::TFSSDPost::ssd_post_process@libxnnpp-xnnpp.so",
    "vitis::ai::applyNMS@libxnnpp-xnnpp.so",
    "vitis::ai::bn@libxnnpp-xnnpp.so",
    "vitis::ai::char2float@libvitis_ai_library-math.so",
    "vitis::ai::classification_post_process@libxnnpp-xnnpp.so",
    "vitis::ai::convert_color@libxnnpp-xnnpp.so",
    "vitis::ai::correct_region_boxes@libxnnpp-xnnpp.so",
    "vitis::ai::detect@libxnnpp-xnnpp.so",
    "vitis::ai::div_ceil@libvitis_ai_library-math.so",
    "vitis::ai::div_floor@libvitis_ai_library-math.so",
    "vitis::ai::dpssd::SSDdetector::detect@libxnnpp-xnnpp.so",
    "vitis::ai::drawpoly@libxnnpp-xnnpp.so",
    "vitis::ai::expand@libvitis_ai_library-math.so",
    "vitis::ai::expand_and_align@libvitis_ai_library-math.so",
    "vitis::ai::expand_crop@libvitis_ai_library-math.so",
    "vitis::ai::face_detect_post_process@libxnnpp-xnnpp.so",
    "vitis::ai::face_landmark_post_process@libxnnpp-xnnpp.so",
    "vitis::ai::findLines@libxnnpp-xnnpp.so",
    "vitis::ai::find_peak_neon@libxnnpp-xnnpp.so",
    "vitis::ai::fixpos2step@libvitis_ai_library-math.so",
    "vitis::ai::float2result_12@libvitis_ai_library-math.so",
    "vitis::ai::float2result_16@libvitis_ai_library-math.so",
    "vitis::ai::float2result_24@libvitis_ai_library-math.so",
    "vitis::ai::float2result_2@libvitis_ai_library-math.so",
    "vitis::ai::float2result_32@libvitis_ai_library-math.so",
    "vitis::ai::float2result_3@libvitis_ai_library-math.so",
    "vitis::ai::float2result_4@libvitis_ai_library-math.so",
    "vitis::ai::float2result_6@libvitis_ai_library-math.so",
    "vitis::ai::float2result_8@libvitis_ai_library-math.so",
    "vitis::ai::getPoses@libxnnpp-xnnpp.so",
    "vitis::ai::getResult@libxnnpp-xnnpp.so",
    "vitis::ai::getScale@libvitis_ai_library-math.so",
    "vitis::ai::getTable@libvitis_ai_library-math.so",
    "vitis::ai::globalAvePool@libvitis_ai_library-math.so",
    "vitis::ai::open_pose_post_process@libxnnpp-xnnpp.so",
    "vitis::ai::overlap@libxnnpp-xnnpp.so",
    "vitis::ai::pose_detect_post_process@libxnnpp-xnnpp.so",
    "vitis::ai::reid_post_process@libxnnpp-xnnpp.so",
    "vitis::ai::seg_color_c16@libxnnpp-xnnpp.so",
    "vitis::ai::segmentation_post_process_8UC1@libxnnpp-xnnpp.so",
    "vitis::ai::segmentation_post_process_8UC3@libxnnpp-xnnpp.so",
    "vitis::ai::sigmoid@libxnnpp-xnnpp.so",
    "vitis::ai::slurp@libxnnpp-xnnpp.so",
    "vitis::ai::softmax@libvitis_ai_library-math.so",
    "vitis::ai::tiling@libvitis_ai_library-math.so",
    "vitis::ai::topk@libxnnpp-xnnpp.so",
    "vitis::ai::yolov2_post_process@libxnnpp-xnnpp.so",
    "vitis::ai::yolov3_post_process@libxnnpp-xnnpp.so",
    "vitis::ai::yuv2bgr@libvitis_ai_library-math.so"
  ],
  "trace_vart": [
    "xir::XrtCu::run@libvart-dpu-controller.so",
    "DpuRunnerEdge::execute_async@libvart-dpu-runner.so"
  ],
  "trace_opencv": [
    "cv::imread",
    "cv::imshow",
    "cv::resize"
  ]
}
